fiaclient/__init__.py
fiaclient/fiaclient.py
fiaclient-1.1.9.dist-info/METADATA
fiaclient-1.1.9.dist-info/RECORD
fiaclient-1.1.9.dist-info/WHEEL
fiaclient-1.1.9.dist-info/top_level.txt
